Metadata-Version: 2.1
Name: pyndas
Version: 0.0.4
Summary: Library for MongoDB data transformation and redundancy removal
Home-page: https://github.com/mfaisal-Ash/pyndas
Download-URL: https://github.com/mfaisal-Ash/pyndas/archive/refs/tags/v0.0.4.tar.gz
Author: Mfaidiq
Author-email: faisalsidiq14@gmail.com
Keywords: pyndas,py-ndas
Classifier: Development Status :: 3 - Alpha
Classifier: Intended Audience :: Developers
Classifier: Topic :: Software Development :: Build Tools
Classifier: License :: OSI Approved :: MIT License
Classifier: Programming Language :: Python :: 3
Classifier: Programming Language :: Python :: 3.4
Classifier: Programming Language :: Python :: 3.5
Classifier: Programming Language :: Python :: 3.6
Classifier: Programming Language :: Python :: 3.7
Classifier: Programming Language :: Python :: 3.8
Classifier: Programming Language :: Python :: 3.9
Classifier: Programming Language :: Python :: 3.11
Classifier: Programming Language :: Python :: 3.12
License-File: LICENSE
Requires-Dist: pymongo
Requires-Dist: time
